juicy_serato/__init__.py
juicy_serato/__main__.py
juicy_serato/_juicer.py
juicy_serato/cli/__init__.py
juicy_serato/cli/cli_copy.py
juicy_serato/cli/cli_inject.py
juicy_serato/djuced/__init__.py
juicy_serato/djuced/djuced_db_parser.py
juicy_serato/djuced/djuiced_db_models.py
juicy_serato/gui/__init__.py
juicy_serato/serato/__init__.py
juicy_serato/serato/serato_db_parser.py
juicy_serato/serato/serato_mappings.py
juicy_serato/serato/serato_structs.py
juicy_serato/serato/serato_utils.py
juicy_serato-0.0.2.dist-info/LICENSE
juicy_serato-0.0.2.dist-info/METADATA
juicy_serato-0.0.2.dist-info/WHEEL
juicy_serato-0.0.2.dist-info/entry_points.txt
juicy_serato-0.0.2.dist-info/top_level.txt
juicy_serato-0.0.2.dist-info/RECORD
