Metadata-Version: 2.1
Name: juicy_serato
Version: 0.0.2
Summary: Write song Cue data from the DJuced database to audio files in a Serato-compatible fromat
Author-email: Davis_Software <davissoftware6@gmail.com>
Project-URL: Homepage, https://github.com/Davis-Software/JuicedSerato
Project-URL: Issues, https://github.com/Davis-Software/JuicedSerato/issues
Classifier: Programming Language :: Python :: 3
Classifier: License :: OSI Approved :: MIT License
Classifier: Operating System :: OS Independent
Requires-Python: >=3.8
License-File: LICENSE
Requires-Dist: sqlalchemy
Requires-Dist: click
Requires-Dist: mutagen
